twister2/TSetContext.py
twister2/Twister2Environment.py
twister2/__init__.py
twister2/utils.py
twister2/data/DataObject.py
twister2/data/DataPartition.py
twister2/data/__init__.py
twister2/tset/KeyedTSet.py
twister2/tset/TLink.py
twister2/tset/TSet.py
twister2/tset/__init__.py
twister2/tset/fn/PartitionFunc.py
twister2/tset/fn/SourceFunc.py
twister2/tset/fn/__init__.py
twister2/tset/fn/factory/GenericFunctions.py
twister2/tset/fn/factory/PartitionFunctions.py
twister2/tset/fn/factory/TSetFunctions.py
twister2/tset/fn/factory/__init__.py
twister2-0.2.4.dist-info/LICENSE
twister2-0.2.4.dist-info/METADATA
twister2-0.2.4.dist-info/WHEEL
twister2-0.2.4.dist-info/top_level.txt
twister2-0.2.4.dist-info/RECORD
