Metadata-Version: 2.1
Name: twister2
Version: 0.2.4
Summary: Twister2 is a composable big data environment supporting streaming, data pipelines and analytics. Our vision is to build robust, simple to use data analytics solutions that can leverage both clouds and high performance computing infrastructure.
Home-page: https://github.com/DSC-SPIDAL/twister2
Author: Twister2 Developers
Author-email: twister2@googlegroups.com
License: UNKNOWN
Platform: UNKNOWN
Classifier: Programming Language :: Python :: 3
Classifier: License :: OSI Approved :: Apache Software License
Classifier: Operating System :: OS Independent
Requires-Python: >=3.7
Requires-Dist: cloudpickle
Requires-Dist: jep (==3.9.0)
Requires-Dist: numpy
Requires-Dist: py4j
